{"name":"陈皮糖","slug":"blog-author","avatar":"https://picsum.photos/seed/picsum/200/300","link":"/","description":"uniapp技术分享","socials":{"github":"","twitter":"","stackoverflow":"","wechat":"","qq":"","weibo":"","zhihu":"","csdn":"","juejin":"","customs":{}},"post_list":[{"title":"","uid":"f73a8e23e6f6f669cf99c7dba8fa0722","slug":"hexo","date":"2024-08-17T14:02:18.489Z","updated":"2024-08-17T14:26:08.454Z","comments":true,"path":"api/articles/hexo.json","keywords":null,"cover":null,"text":"Hexo搭建个人博客介绍Hexo是一个基于Node.js的静态博客框架，可以帮助你快速搭建一个个人博客。本文将介绍如何使用Hexo搭建个人博客。 准备工作在开始...","permalink":"/post/hexo","photos":[],"count_time":{"symbolsCount":"1.2k","symbolsTime":"1 mins."},"categories":[],"tags":[],"author":{"name":"陈皮糖","slug":"blog-author","avatar":"https://picsum.photos/seed/picsum/200/300","link":"/","description":"uniapp技术分享","socials":{"github":"","twitter":"","stackoverflow":"","wechat":"","qq":"","weibo":"","zhihu":"","csdn":"","juejin":"","customs":{}}}}],"categories":0,"tags":0,"word_count":"1.2k","post_count":1}